xui_api/__init__.py
xui_api/async_3xapi/__init__.py
xui_api/async_3xapi/api_3xui.py
xui_api/async_3xapi/api_client.py
xui_api/async_3xapi/api_database.py
xui_api/async_3xapi/api_inbound.py
xui_api/async_3xapi/api_info.py
xui_api/client/__init__.py
xui_api/client/client_model.py
xui_api/inbound/__init__.py
xui_api/inbound/inbound_model.py
xui_api/inbound/model.py
xui_api/inbound/settings.py
xui_api/inbound/sniffing.py
xui_api/inbound/stream_settings.py
xui_api/utils/__init__.py
xui_api/utils/null_logger.py
xui_api-0.1.0.dist-info/LICENSE
xui_api-0.1.0.dist-info/METADATA
xui_api-0.1.0.dist-info/WHEEL
xui_api-0.1.0.dist-info/top_level.txt
xui_api-0.1.0.dist-info/RECORD
