Metadata-Version: 2.1
Name: xui_api
Version: 0.1.0
Summary: Модуль для взаимодействия с XUI API, включая управление входящими соединениями и клиентами.
Home-page: https://github.com/Timophey999/connectXUI.git
Author: Timofey Mikheev
Author-email: timoxa.m.is@icloud.com
Classifier: Development Status :: 3 - Alpha
Classifier: Intended Audience :: Developers
Classifier: License :: OSI Approved :: MIT License
Classifier: Programming Language :: Python :: 3
Classifier: Programming Language :: Python :: 3.10
Requires-Python: >=3.7
License-File: LICENSE
Requires-Dist: aiohttp
Requires-Dist: pydantic
Requires-Dist: pytest
Requires-Dist: aioresponses
